{
  "name": "Roxie Morris",
  "age": 29,
  "address": {
    "street": "Wehut Avenue",
    "city": "Liskuaze",
    "state": "IL",
    "zip": "76937"
  },
  "contact": {
    "phone": "(853) 412-9716",
    "servicePhone": "800167887"
  },
  "birthday": "1992-12-26T14:58:25.192Z",
  "ip": "175.4.139.250",
  "foo": "bar",
  "profile": {
    "about": "Ol po lovvu likowub cepevo sufokpu fu kete sukkisuc ukeduro johiaj heub migo zazujog ce juk majjelke def. Tukwepig idsodul jujebin id pooja iphenwo se zor wukko cedvod obuanu co huosi le de zufu. Wugulfef be mijli awa vetewag lausaaw dogtani nin tekidafut zuuzgo naw wogopev. Orute pied loijaemo sil nodlubwi uziupgeg rusid una dejzuracu fo pakehpod pu. Neltah hawpe hoin muwoz kepevaz vo tuluwog wep mila suhwule liz uhu cu timajtad fo arpok mitenucut.",
    "bio": "Nicaj ehi nib putjul dimdiz wo kida zeigigu cupsob muwaw dumoj puogo ipveddoc igni. Fo bozoghek mozunu fezuboj hopip obe howeuf lazukat mor hev cauj lovbuur sujkifoba letuten naculah gezeb. Va aje eno hihihin cirihi iboici zo refbobzon piwi co cam elgogi wem sobaskan zebbopi ceg. Azaca uje ibde micgah nu ezuelome viv robdur mij zaivegal ohadadow mu. Ifloh pib nu guwopeiwi vucimgig jig falaw ro en cow beis ziv bin fevor zibvaz gukdodi gekugisil gable. Komsije biszasso nov na fuip moh gizik law ofeagda jefrodij atlig elge tew zokilbi oha ber bi."
  },
  "apiKey": "814a53926be92c62c303529a34b81919b161ae9b3358e3c0edd65e3b9ad9d6c1",
  "currency": {
    "code": "CNY",
    "name": "China Yuan Renminbi"
  }
}