{
  "name": "Gene Gray",
  "age": 58,
  "address": {
    "street": "Sepja Turnpike",
    "city": "Bopdaliz",
    "state": "WA",
    "zip": "53242"
  },
  "contact": {
    "phone": "(489) 527-3587",
    "servicePhone": "800618147"
  },
  "birthday": "1962-09-18T08:46:39.712Z",
  "ip": "241.249.9.81",
  "foo": "bar",
  "profile": {
    "about": "Jorsef no luktut una visfazu laihke ocalaf ecmu lis ilgohpa jafkik locwar habumeh. Luhjoh jupez okurudi ebba oluaseji eli pe mefiwa evezowi widagzas daepod amlo paf ofobiap caclan pi va. Fob memniw voma ridgem pew majic deblik su bedav ihziwhub boj lobisag wu udo. Uwo gije doodwup wik le le imefe nas dunfu sitrardol fuopnag luso lipda uwozazi ebo uzomejji. Bosdak ba lar heszohme hubzi rejsad ba welwizmar uzahodag nam eboceda nubdem tereb vi of hoval.",
    "bio": "Mimeto pa zooshe kohevcu etbikeh pugjo ta zahfil surfibbaj lemotuuf co ceaci el fedomami nowu. Faltiwovi lifu weihasip ubuza lif dapu ido eviraci dosaku nejafu lemboffug uzu tutezen no. Ivodewtaw ujne dira zajolibih sezdej afo rodek re fi vac cilakwad guru ti zehadko loj. Gahrus fupormu bo lomrose lualu lapmoka adiso vegcej ena not ubihegcoc es pir teuketi."
  },
  "apiKey": "51f29e85fb890a0b8d4c49db8d40f1a9a3d2393ca956ad4e1fae4c4bb9669da4",
  "currency": {
    "code": "SVC",
    "name": "El Salvador Colon"
  }
}