{
  "name": "Alice Mason",
  "age": 34,
  "address": {
    "street": "Neje Trail",
    "city": "Dumosdo",
    "state": "MA",
    "zip": "04676"
  },
  "contact": {
    "phone": "(501) 969-7170",
    "servicePhone": "800179368"
  },
  "birthday": "1981-09-10T17:39:38.877Z",
  "ip": "2.2.67.192",
  "foo": "bar",
  "profile": {
    "about": "Kofbatad fijguuw pujaz puzhec ercepi ji ohhot hisdi roku he hitizen vivi lenemgob va nu. Teata epo ewiukedo eho jubuzewu tuh liz piz nu winbum envuz boezaf mukni tim gopok. Of sevoji fewpik tu iroja gautke lolet hih budtol atifulku lipateco zeapkut.",
    "bio": "Tauj ejpef ibiudfof omofinil irealtak cushulib ded ucuzi vabidte huvicus silojoat soz izwem zipamreh guijugeb touswa ruoza jicoer. Enodalfen mini pifoh fa pinhip po hep keojiata tinoki tiwu vuwgane gogbin hutuw nik zovimse ti hozoncid. Dihnom meet ew zuuwiki lelkamwe kehzur itke rinubah ocekebkap fola obfisaf ga futeva lulrol ehgasir ho sa. Cajagab kakahuga ka omamej hi taswub zinom he ci feik ja uvlifi hijopbow ecu ev. Fer fezhodic ji fis wezsod ifudu vul pu kootij sobla johan wakebwe."
  },
  "apiKey": "b73d3e7f35bcbcc76b65ea2b6e68571ec8f6b6863dcec135ab3876ac679bb612",
  "currency": {
    "code": "SGD",
    "name": "Singapore Dollar"
  }
}